[{"id":228,"created":1691602669,"last_edited":1691602669,"order":1,"summit_id":49,"is_published":true,"side_image":null,"header_image":null,"header_image_mobile":null,"carousel_advertise_image":null,"marquee":"","intro":"","external_link":"","video_link":"","chat_link":"","featured_event_id":0,"header_image_alt_text":"","side_image_alt_text":"","header_image_mobile_alt_text":"","carousel_advertise_image_alt_text":"","show_logo_in_event_page":true,"members":[90654,90670],"company":{"id":3,"created":1580138376,"last_edited":1580138376,"name":"Tipit , LLC","url":null,"display_on_site":false,"featured":false,"city":null,"state":null,"country":null,"description":null,"industry":null,"contributions":null,"contact_email":null,"member_level":"None","admin_email":null,"overview":null,"products":null,"commitment":null,"commitment_author":null,"logo":null,"big_logo":null,"color":"#f0f0ee","sponsorships":[616],"project_sponsorships":[]},"sponsorship":{"id":2048,"widget_title":"","lobby_template":null,"expo_hall_template":null,"sponsor_page_template":null,"event_page_template":null,"sponsor_page_use_disqus_widget":false,"sponsor_page_use_live_event_widget":false,"sponsor_page_use_schedule_widget":false,"sponsor_page_use_banner_widget":false,"badge_image":null,"badge_image_alt_text":"","summit_id":49,"order":1,"should_display_on_expo_hall_page":false,"should_display_on_lobby_page":false,"type":{"id":3,"created":1579890943,"last_edited":1579890943,"name":"Gold","label":"not sure??","order":3,"size":"Medium"}},"ads":[],"materials":[],"social_networks":[]}]